odatix/__init__.py
odatix/odatix_explorer.py
odatix/odatix_main.py
odatix/version.txt
odatix/components/__init__.py
odatix/components/clean.py
odatix/components/export_benchmark.py
odatix/components/export_results.py
odatix/components/generate_configs.py
odatix/components/motd.py
odatix/components/replace_params.py
odatix/components/run_fmax_synthesis.py
odatix/components/run_range_synthesis.py
odatix/components/run_simulations.py
odatix/explorer/__init__.py
odatix/explorer/content_lib.py
odatix/explorer/css_helper.py
odatix/explorer/explorer_app.py
odatix/explorer/figures.py
odatix/explorer/legend.py
odatix/explorer/navigation.py
odatix/explorer/themes.py
odatix/explorer/assets/favicon.ico
odatix/explorer/assets/style.css
odatix/explorer/assets/icons/sidebar-panel-collapse-icon.svg
odatix/explorer/assets/icons/sidebar-panel-expand-icon.svg
odatix/explorer/assets/preview/columns.svg
odatix/explorer/assets/preview/lines.svg
odatix/explorer/assets/preview/overview.png
odatix/explorer/assets/preview/radar.svg
odatix/explorer/assets/preview/scatter.svg
odatix/explorer/assets/preview/scatter3d.svg
odatix/explorer/behaviors/columns.py
odatix/explorer/behaviors/lines.py
odatix/explorer/behaviors/overview.py
odatix/explorer/behaviors/radar.py
odatix/explorer/behaviors/scatter.py
odatix/explorer/behaviors/scatter3d.py
odatix/explorer/behaviors/setup_callbacks.py
odatix/explorer/pages/columns.py
odatix/explorer/pages/home.py
odatix/explorer/pages/lines.py
odatix/explorer/pages/not_found_404.py
odatix/explorer/pages/overview.py
odatix/explorer/pages/radar.py
odatix/explorer/pages/scatter.py
odatix/explorer/pages/scatter3d.py
odatix/lib/__init__.py
odatix/lib/ansi_to_curses.py
odatix/lib/architecture_handler.py
odatix/lib/check_tool.py
odatix/lib/config_generator.py
odatix/lib/get_from_dict.py
odatix/lib/hard_settings.py
odatix/lib/job_output_formatter.py
odatix/lib/parallel_job_handler.py
odatix/lib/param_domain.py
odatix/lib/prepare_work.py
odatix/lib/printc.py
odatix-3.6.1.dist-info/METADATA
odatix-3.6.1.dist-info/WHEEL
odatix-3.6.1.dist-info/entry_points.txt
odatix-3.6.1.dist-info/top_level.txt
odatix-3.6.1.dist-info/RECORD
