Metadata-Version: 2.2
Name: odatix
Version: 3.6.1
Summary: A FPGA/ASIC toolbox for design space exploration
Home-page: https://github.com/jsaussereau/Asterism
Author: Jonathan Saussereau
Author-email: jonathan.saussereau@ims-bordeaux.fr
Classifier: Programming Language :: Python :: 3
Classifier: License :: OSI Approved :: GNU General Public License v3 (GPLv3)
Classifier: Operating System :: POSIX
Requires-Python: >=3.6
Requires-Dist: PyYAML
Requires-Dist: argcomplete
Requires-Dist: dash
Requires-Dist: Flask
Requires-Dist: numpy
Requires-Dist: pandas
Requires-Dist: plotly
Requires-Dist: waitress
Dynamic: author
Dynamic: author-email
Dynamic: classifier
Dynamic: description
Dynamic: description-content-type
Dynamic: home-page
Dynamic: requires-dist
Dynamic: requires-python
Dynamic: summary
